iverilog-adder/modules/or_module.v
module or1(input wire a,b,output wire y);
assign y = a|b;

endmodule

iverilog-adder/modules/and_module.v
module and1(input wire c,b,output wire x);
assign x = c&b;

endmodule

iverilog-circuit/circuit2.v
module circuit2(a,b,c,z);
    input a,b,c;
    output z;
    wire x;
    wire o;
    wire n;

and1 andmod1(c,b,x);
or1 ormod1(x,a,n);
and1 andmod2(a,b,o);
or1 ormod2(n,o,z);
endmodule

iverilog-circuit/cir2_testbench.v
module tb;
reg t_a;
reg t_b;
reg t_c;
wire t_x;
wire t_n;
wire t_z;
wire t_o;
circuit2 c2(.a(t_a),.b(t_b),.c(t_c),.z(t_z));
initial begin $dumpfile("dump.vcd");
$dumpvars(0,tb);
end
initial begin $monitor(t_a,t_b,t_c,t_z);
t_a=1'b0;
t_b=1'b0;
t_c=1'b0;
#10
t_a=1'b0;
t_b=1'b0;
t_c=1'b1;
#10
t_a=1'b0;
t_b=1'b1;
t_c=1'b0;
#10
t_a=1'b0;
t_b=1'b1;
t_c=1'b1;
#10
t_a=1'b1;
t_b=1'b0;
t_c=1'b0;
#10
t_a=1'b1;
t_b=1'b0;
t_c=1'b1;
#10
t_a=1'b1;
t_b=1'b1;
t_c=1'b0;
#10
t_a=1'b1;
t_b=1'b1;
t_c=1'b1;

end
endmodule

iverilog-circuit/dump.vcd
$date
	Thu Aug 24 10:04:26 2023
$end
$version
	Icarus Verilog
$end
$timescale
	1s
$end
$scope module tb $end
$var wire 1 ! t_z $end
$var reg 1 " t_a $end
$var reg 1 # t_b $end
$var reg 1 $ t_c $end
$scope module c2 $end
$var wire 1 " a $end
$var wire 1 # b $end
$var wire 1 $ c $end
$var wire 1 ! z $end
$var wire 1 % x $end
$var wire 1 & o $end
$var wire 1 ' n $end
$scope module andmod1 $end
$var wire 1 # b $end
$var wire 1 $ c $end
$var wire 1 % x $end
$upscope $end
$scope module andmod2 $end
$var wire 1 # b $end
$var wire 1 " c $end
$var wire 1 & x $end
$upscope $end
$scope module ormod1 $end
$var wire 1 % a $end
$var wire 1 " b $end
$var wire 1 ' y $end
$upscope $end
$scope module ormod2 $end
$var wire 1 ' a $end
$var wire 1 & b $end
$var wire 1 ! y $end
$upscope $end
$upscope $end
$upscope $end
$enddefinitions $end
$comment Show the parameter values. $end
$dumpall
$end
#0
$dumpvars
0'
0&
0%
0$
0#
0"
0!
$end
#10
1$
#20
0$
1#
#30
1!
1'
1%
1$
#40
0%
0$
0#
1"
#50
1$
#60
1&
0$
1#
#70
1%
1$
