iverilog-adder/modules/or_module.v
module or1(input wire a,b,output wire y);
assign y = a|b;

endmodule

iverilog-adder/modules/and_module.v
module and1(input wire c,b,output wire x);
assign x = c&b;

endmodule

iverilog-adder/xor_module.v
module xor1(input wire a,b,output wire y);
assign y = a^b;

endmodule

iverilog-adder/fa_module.v
module fa_module1(a,b,cin,sum,cout);
    input a,b,cin;
    output sum,cout;
    wire x,y,z;

and1 andmod1(a,b,x);
xor1 xormod1(a,b,y);
xor1 xormod2(y,cin,sum);
and1 andmod2(y,cin,z);
or1 ormod1(z,x,cout);
endmodule

iverilog-adder/tb.v
module tb;
reg t_a;
reg t_b;
wire t_x;
wire t_y;
wire t_z;
wire t_sum;
reg t_cin;
wire t_cout;
fa_module1 a1(.a(t_a),.b(t_b),.cin(t_cin),.sum(t_sum),.cout(t_cout));
initial begin $dumpfile("dump.vcd");
$dumpvars(0,tb);
end
initial begin $monitor(t_a,t_b,t_cin,t_sum,t_cout);
t_a=1'b0;
t_b=1'b0;
t_cin=1'b0;
#10
t_a=1'b0;
t_b=1'b0;
t_cin=1'b1;
#10
t_a=1'b0;
t_b=1'b1;
t_cin=1'b0;
#10
t_a=1'b0;
t_b=1'b1;
t_cin=1'b1;
#10
t_a=1'b1;
t_b=1'b0;
t_cin=1'b0;
#10
t_a=1'b1;
t_b=1'b0;
t_cin=1'b1;
#10
t_a=1'b1;
t_b=1'b1;
t_cin=1'b0;
#10
t_a=1'b1;
t_b=1'b1;
t_cin=1'b1;
#10
t_a=1'b0;
t_b=1'b0;
t_cin=1'b0;

end
endmodule

iverilog-adder/dump.vcd
$date
	Thu Aug 24 14:35:15 2023
$end
$version
	Icarus Verilog
$end
$timescale
	1s
$end
$scope module tb $end
$var wire 1 ! t_sum $end
$var wire 1 " t_cout $end
$var reg 1 # t_a $end
$var reg 1 $ t_b $end
$var reg 1 % t_cin $end
$scope module a1 $end
$var wire 1 # a $end
$var wire 1 $ b $end
$var wire 1 % cin $end
$var wire 1 & z $end
$var wire 1 ' y $end
$var wire 1 ( x $end
$var wire 1 ! sum $end
$var wire 1 " cout $end
$scope module andmod1 $end
$var wire 1 $ b $end
$var wire 1 # c $end
$var wire 1 ( x $end
$upscope $end
$scope module andmod2 $end
$var wire 1 % b $end
$var wire 1 & x $end
$var wire 1 ' c $end
$upscope $end
$scope module ormod1 $end
$var wire 1 & a $end
$var wire 1 ( b $end
$var wire 1 " y $end
$upscope $end
$scope module xormod1 $end
$var wire 1 # a $end
$var wire 1 $ b $end
$var wire 1 ' y $end
$upscope $end
$scope module xormod2 $end
$var wire 1 ' a $end
$var wire 1 % b $end
$var wire 1 ! y $end
$upscope $end
$upscope $end
$upscope $end
$enddefinitions $end
$comment Show the parameter values. $end
$dumpall
$end
#0
$dumpvars
0(
0'
0&
0%
0$
0#
0"
0!
$end
#10
1!
1%
#20
1'
0%
1$
#30
1"
1&
0!
1%
#40
0"
0&
1!
0%
0$
1#
#50
1"
1&
0!
1%
#60
0&
1(
0'
0%
1$
#70
1!
1%
#80
0"
0!
0(
0%
0$
0#
